{
  "externalChangelogURL": "https://github.com/kubermatic/kubermatic/blob/main/docs/changelogs/CHANGELOG-2.20.md#v22014",
  "entries": [
    {
        "category": "fixed",
        "description": "Fix partially deployed CSI validating webhook on CCM/CSI migrated clusters on vSphere."
    },
    {
        "category": "fixed",
        "description": "Set proper NodePort range in Cilium config if non-default range is used."
    },
    {
        "category": "fixed",
        "description": "Include tunneling agent IP in apiserver's TLS cert SANs."
    }
  ]
}
